sufi/__init__.py
sufi/filters.py
sufi/pentagram.png
sufi/red.png
sufi/shield.png
sufi/utility.py
sufi/videoProcessing.py
sufi-1.0.2.7.dist-info/LICENCE
sufi-1.0.2.7.dist-info/METADATA
sufi-1.0.2.7.dist-info/WHEEL
sufi-1.0.2.7.dist-info/top_level.txt
sufi-1.0.2.7.dist-info/RECORD
