Metadata-Version: 2.1
Name: sufi
Version: 1.0.2.7
Summary: apply different types of filters on image
Home-page: https://github.com/sunnykumar1516/sufi
Author: sunny kumar
Author-email: sunnykumar1516@gmail.com
License: MIT
Requires-Python: >=3.8
License-File: LICENCE
Requires-Dist: numpy (>=1.2)
Requires-Dist: opencv-python (>=4)
Requires-Dist: mediapipe (>=0.10.5)
